pytimber/LHCBSRT.py
pytimber/__init__.py
pytimber/dataquery.py
pytimber/localdate.py
pytimber/pytimber.py
pytimber/timberdata.py
pytimber/toolbox.py
pytimber-2.2.11.dist-info/DESCRIPTION.rst
pytimber-2.2.11.dist-info/METADATA
pytimber-2.2.11.dist-info/RECORD
pytimber-2.2.11.dist-info/WHEEL
pytimber-2.2.11.dist-info/metadata.json
pytimber-2.2.11.dist-info/top_level.txt
