Metadata-Version: 2.0
Name: pytimber
Version: 2.2.11
Summary: A Python wrapping of CALS API
Home-page: https://github.com/rdemaria/pytimber
Author: Riccardo De Maria
Author-email: riccardo.de.maria@cern.ch
License: UNKNOWN
Platform: UNKNOWN
Requires-Dist: JPype1 (>=0.6.1)
Requires-Dist: cmmnbuild-dep-manager (>=2.0.0)
